IMFlow.cp312-win_amd64.pyd
imagematchingflow-0.1.1.dist-info/METADATA
imagematchingflow-0.1.1.dist-info/WHEEL
imagematchingflow-0.1.1.dist-info/top_level.txt
imagematchingflow-0.1.1.dist-info/RECORD
